litelama/__init__.py
litelama/base.py
litelama/config.yaml
litelama/depthwise_sep_conv.py
litelama/fake_fakes.py
litelama/ffc.py
litelama/litelama.py
litelama/model.py
litelama/multidilated_conv.py
litelama/multiscale.py
litelama/pix2pixhd.py
litelama/spatial_transform.py
litelama/squeeze_excitation.py
litelama-0.1.7.dist-info/METADATA
litelama-0.1.7.dist-info/WHEEL
litelama-0.1.7.dist-info/RECORD
