Metadata-Version: 2.1
Name: litelama
Version: 0.1.7
Summary: A lightweight LAMA model inference wrapper
Author-email: novita <novitalabs@gmail.com>
Requires-Python: >=3.8
Requires-Dist: kornia>=0.7.0
Requires-Dist: numpy>=1.24.4
Requires-Dist: omegaconf>=2.3.0
Requires-Dist: opencv-python>=4.8.0.76
Requires-Dist: pillow>=10.0.1
Requires-Dist: requests>=2.31.0
Requires-Dist: safetensors>=0.3.3
Requires-Dist: torch>=2.0.1
